passive_server/__init__.py
passive_server/active_host.py
passive_server/common_func.py
passive_server/display_log.py
passive_server/enum_sece_data_type.py
passive_server/exception.py
passive_server/factory.py
passive_server/manual.xlsx
passive_server/models_class.py
passive_server/passive_equipment.py
passive_server/passive_host.py
passive_server/passive_server.py
passive_server/plc_address_operation.py
passive_server/secs_config.py
passive_server-1.3.0.dist-info/METADATA
passive_server-1.3.0.dist-info/WHEEL
passive_server-1.3.0.dist-info/RECORD
