Metadata-Version: 2.4
Name: passive_server
Version: 1.3.0
Summary: 作为服务端的设备
Author: WeiLiu
Author-email: 183074632@qq.com
Requires-Python: >=3.11,<3.13
Classifier: Programming Language :: Python :: 3
Classifier: Programming Language :: Python :: 3.11
Classifier: Programming Language :: Python :: 3.12
Requires-Dist: alembic (>=1.14.0,<2.0.0)
Requires-Dist: bar-tender-api (>=1.0.0)
Requires-Dist: cffi (>=1.17.0,<2.0.0)
Requires-Dist: gkg-laser (>=1.0.0)
Requires-Dist: hslcommunication (>=1.2.0,<2.0.0)
Requires-Dist: inovance-tag-cyg (>=1.9.0)
Requires-Dist: mitsubishi-plc (>=1.6.0)
Requires-Dist: modbus-api (>=1.14.0)
Requires-Dist: modbus-tk (>=1.1.4,<2.0.0)
Requires-Dist: mysql-api (>=1.11.0)
Requires-Dist: openpyxl (>=3.1.5,<4.0.0)
Requires-Dist: pandas (>=2.2.3,<3.0.0)
Requires-Dist: pillow (>=10.4.0,<11.0.0)
Requires-Dist: pyairtable (>=2.3.3,<3.0.0)
Requires-Dist: pymysql (>=1.1.1,<2.0.0)
Requires-Dist: python-snap7 (>=2.0.2,<3.0.0)
Requires-Dist: pythonnet (>=3.0.3,<4.0.0)
Requires-Dist: secsgem_cyg (>=1.18.0)
Requires-Dist: siemens-plc (>=1.7.0)
Requires-Dist: socket-cyg (>=1.10.0)
Requires-Dist: sqlalchemy (>=2.0.36,<3.0.0)
Requires-Dist: suds-community (>=1.2.0,<2.0.0)
Requires-Dist: websockets (>=14.1,<15.0)
